ghowlauth/__init__.py
ghowlauth/common.py
ghowlauth/ghowl.py
sqre_ghowlauth-0.0.10.dist-info/DESCRIPTION.rst
sqre_ghowlauth-0.0.10.dist-info/METADATA
sqre_ghowlauth-0.0.10.dist-info/RECORD
sqre_ghowlauth-0.0.10.dist-info/WHEEL
sqre_ghowlauth-0.0.10.dist-info/metadata.json
sqre_ghowlauth-0.0.10.dist-info/top_level.txt
