Metadata-Version: 2.0
Name: sqre-ghowlauth
Version: 0.0.10
Summary: JupyterHub authenticator that uses GH orgs as whitelists
Home-page: https://github.com/lsst-sqre/ghowlauth
Author: Adam Thornton
Author-email: frossie@lsst.org
License: MIT
Keywords: lsst
Platform: UNKNOWN
Classifier: Development Status :: 4 - Beta
Classifier: Programming Language :: Python :: 2.7
Classifier: Programming Language :: Python :: 3.5
Classifier: License :: OSI Approved :: MIT License
Requires-Dist: oauthenticator (>=0.5.1)
Requires-Dist: tornado (>=4.1)
